yabplot/__init__.py
yabplot/plotting.py
yabplot/scene.py
yabplot/utils.py
yabplot/data/__init__.py
yabplot/data/registry.txt
yabplot-0.1.2.dist-info/licenses/LICENSE
yabplot-0.1.2.dist-info/METADATA
yabplot-0.1.2.dist-info/WHEEL
yabplot-0.1.2.dist-info/top_level.txt
yabplot-0.1.2.dist-info/RECORD
