Metadata-Version: 2.4
Name: yabplot
Version: 0.1.2
Summary: yet another brain plot
Requires-Python: >=3.10
License-File: LICENSE
Requires-Dist: ipywidgets>=8.1.8
Requires-Dist: nibabel>=5.3.2
Requires-Dist: pandas>=2.3.3
Requires-Dist: pooch>=1.8.2
Requires-Dist: pyvista>=0.46.4
Requires-Dist: scikit-image>=0.25.2
Requires-Dist: trame>=3.12.0
Requires-Dist: trame-vtk>=2.10.0
Requires-Dist: trame-vuetify>=3.1.0
Provides-Extra: docs
Requires-Dist: mkdocs; extra == "docs"
Requires-Dist: mkdocs-jupyter>=0.25.1; extra == "docs"
Requires-Dist: mkdocs-material; extra == "docs"
Requires-Dist: mkdocstrings[python]; extra == "docs"
Dynamic: license-file
